[{"EDGAR Country Code":"ABW","Country":"Aruba","year":"2021","C02 per capita (t CO2\/yr)":11.90779307,"total C02 emissions (Mt CO2\/yr)":1.274133858,"Cumulative CO\u2082 emissions (1970\u20132021 in Mt CO2)":39.277079932,"C02 per GDP (t CO2\/yr)":0.345604683},{"EDGAR Country Code":"AFG","Country":"Afghanistan","year":"2021","C02 per capita (t CO2\/yr)":0.21451583,"total C02 emissions (Mt CO2\/yr)":8.347669018,"Cumulative CO\u2082 emissions (1970\u20132021 in Mt CO2)":192.122011814,"C02 per GDP (t CO2\/yr)":0.108820226},{"EDGAR Country Code":"AGO","Country":"Angola","year":"2021","C02 per capita (t CO2\/yr)":0.721368301,"total C02 emissions (Mt CO2\/yr)":24.4500572,"Cumulative CO\u2082 emissions (1970\u20132021 in Mt CO2)":880.286106186,"C02 per GDP (t CO2\/yr)":0.120279818},{"EDGAR Country Code":"AIA","Country":"Anguilla","year":"2021","C02 per capita (t CO2\/yr)":1.693914681,"total C02 emissions (Mt CO2\/yr)":0.02540872,"Cumulative CO\u2082 emissions (1970\u20132021 in Mt CO2)":0.660051199,"C02 per GDP (t CO2\/yr)":0.120165705},{"EDGAR Country Code":"ALB","Country":"Albania","year":"2021","C02 per capita (t CO2\/yr)":1.559481772,"total C02 emissions (Mt CO2\/yr)":4.591114338,"Cumulative CO\u2082 emissions (1970\u20132021 in Mt CO2)":265.267959361,"C02 per GDP (t CO2\/yr)":0.112456469},{"EDGAR Country Code":"ANT","Country":"Cura\u00e7ao","year":"2021","C02 per capita (t CO2\/yr)":12.41051265,"total C02 emissions (Mt CO2\/yr)":2.035324074,"Cumulative CO\u2082 emissions (1970\u20132021 in Mt CO2)":321.5825598,"C02 per GDP (t CO2\/yr)":0.669930394},{"EDGAR Country Code":"ARE","Country":"United Arab Emirates","year":"2021","C02 per capita (t CO2\/yr)":19.47337626,"total C02 emissions (Mt CO2\/yr)":193.5069399,"Cumulative CO\u2082 emissions (1970\u20132021 in Mt CO2)":5131.25446808,"C02 per GDP (t CO2\/yr)":0.302139359},{"EDGAR Country Code":"ARG","Country":"Argentina","year":"2021","C02 per capita (t CO2\/yr)":4.116435673,"total C02 emissions (Mt CO2\/yr)":189.0020275,"Cumulative CO\u2082 emissions (1970\u20132021 in Mt CO2)":7014.17322276,"C02 per GDP (t CO2\/yr)":0.1918403},{"EDGAR Country Code":"ARM","Country":"Armenia","year":"2021","C02 per capita (t CO2\/yr)":2.302654252,"total C02 emissions (Mt CO2\/yr)":6.769803499,"Cumulative CO\u2082 emissions (1970\u20132021 in Mt CO2)":527.140493678,"C02 per GDP (t CO2\/yr)":0.171269285},{"EDGAR Country Code":"ATG","Country":"Antigua and Barbuda","year":"2021","C02 per capita (t CO2\/yr)":7.338407585,"total C02 emissions (Mt CO2\/yr)":0.777871204,"Cumulative CO\u2082 emissions (1970\u20132021 in Mt CO2)":30.272981508,"C02 per GDP (t CO2\/yr)":0.436329676},{"EDGAR Country Code":"AUS","Country":"Australia","year":"2021","C02 per capita (t CO2\/yr)":14.31488881,"total C02 emissions (Mt CO2\/yr)":367.9069573,"Cumulative CO\u2082 emissions (1970\u20132021 in Mt CO2)":15933.4267263,"C02 per GDP (t CO2\/yr)":0.289881232},{"EDGAR Country Code":"AUT","Country":"Austria","year":"2021","C02 per capita (t CO2\/yr)":7.500022082,"total C02 emissions (Mt CO2\/yr)":66.00769434,"Cumulative CO\u2082 emissions (1970\u20132021 in Mt CO2)":3425.55552041,"C02 per GDP (t CO2\/yr)":0.136621664},{"EDGAR Country Code":"AZE","Country":"Azerbaijan","year":"2021","C02 per capita (t CO2\/yr)":3.645254245,"total C02 emissions (Mt CO2\/yr)":37.10504296,"Cumulative CO\u2082 emissions (1970\u20132021 in Mt CO2)":2113.21642864,"C02 per GDP (t CO2\/yr)":0.253615061},{"EDGAR Country Code":"BDI","Country":"Burundi","year":"2021","C02 per capita (t CO2\/yr)":0.057732707,"total C02 emissions (Mt CO2\/yr)":0.710458691,"Cumulative CO\u2082 emissions (1970\u20132021 in Mt CO2)":14.274336873,"C02 per GDP (t CO2\/yr)":0.08028701},{"EDGAR Country Code":"BEL","Country":"Belgium","year":"2021","C02 per capita (t CO2\/yr)":8.220382226,"total C02 emissions (Mt CO2\/yr)":95.92364019,"Cumulative CO\u2082 emissions (1970\u20132021 in Mt CO2)":6193.59775948,"C02 per GDP (t CO2\/yr)":0.160419071},{"EDGAR Country Code":"BEN","Country":"Benin","year":"2021","C02 per capita (t CO2\/yr)":0.693115169,"total C02 emissions (Mt CO2\/yr)":8.629283856,"Cumulative CO\u2082 emissions (1970\u20132021 in Mt CO2)":126.955691362,"C02 per GDP (t CO2\/yr)":0.200932935},{"EDGAR Country Code":"BFA","Country":"Burkina Faso","year":"2021","C02 per capita (t CO2\/yr)":0.246074118,"total C02 emissions (Mt CO2\/yr)":5.289855324,"Cumulative CO\u2082 emissions (1970\u20132021 in Mt CO2)":72.781080198,"C02 per GDP (t CO2\/yr)":0.109805384},{"EDGAR Country Code":"BGD","Country":"Bangladesh","year":"2021","C02 per capita (t CO2\/yr)":0.623133765,"total C02 emissions (Mt CO2\/yr)":106.8674407,"Cumulative CO\u2082 emissions (1970\u20132021 in Mt CO2)":1745.942611867,"C02 per GDP (t CO2\/yr)":0.106753535},{"EDGAR Country Code":"BGR","Country":"Bulgaria","year":"2021","C02 per capita (t CO2\/yr)":6.332613641,"total C02 emissions (Mt CO2\/yr)":43.64437322,"Cumulative CO\u2082 emissions (1970\u20132021 in Mt CO2)":3378.4569066,"C02 per GDP (t CO2\/yr)":0.269976205},{"EDGAR Country Code":"BHR","Country":"Bahrain","year":"2021","C02 per capita (t CO2\/yr)":21.49922026,"total C02 emissions (Mt CO2\/yr)":37.49464013,"Cumulative CO\u2082 emissions (1970\u20132021 in Mt CO2)":920.523357459,"C02 per GDP (t CO2\/yr)":0.518835735},{"EDGAR Country Code":"BHS","Country":"Bahamas","year":"2021","C02 per capita (t CO2\/yr)":9.860330668,"total C02 emissions (Mt CO2\/yr)":4.042735574,"Cumulative CO\u2082 emissions (1970\u20132021 in Mt CO2)":176.630583411,"C02 per GDP (t CO2\/yr)":0.328066737},{"EDGAR Country Code":"BIH","Country":"Bosnia and Herzegovina","year":"2021","C02 per capita (t CO2\/yr)":4.401509139,"total C02 emissions (Mt CO2\/yr)":15.37006991,"Cumulative CO\u2082 emissions (1970\u20132021 in Mt CO2)":942.049910751,"C02 per GDP (t CO2\/yr)":0.301232507},{"EDGAR Country Code":"BLR","Country":"Belarus","year":"2021","C02 per capita (t CO2\/yr)":6.210952149,"total C02 emissions (Mt CO2\/yr)":58.36431734,"Cumulative CO\u2082 emissions (1970\u20132021 in Mt CO2)":3995.38129954,"C02 per GDP (t CO2\/yr)":0.316367863},{"EDGAR Country Code":"BLZ","Country":"Belize","year":"2021","C02 per capita (t CO2\/yr)":1.56797764,"total C02 emissions (Mt CO2\/yr)":0.635030944,"Cumulative CO\u2082 emissions (1970\u20132021 in Mt CO2)":23.468510129,"C02 per GDP (t CO2\/yr)":0.248926742},{"EDGAR Country Code":"BMU","Country":"Bermuda","year":"2021","C02 per capita (t CO2\/yr)":13.66228132,"total C02 emissions (Mt CO2\/yr)":0.819736879,"Cumulative CO\u2082 emissions (1970\u20132021 in Mt CO2)":34.82055072,"C02 per GDP (t CO2\/yr)":0.165514154},{"EDGAR Country Code":"BOL","Country":"Bolivia","year":"2021","C02 per capita (t CO2\/yr)":1.915616373,"total C02 emissions (Mt CO2\/yr)":22.42803649,"Cumulative CO\u2082 emissions (1970\u20132021 in Mt CO2)":526.78873469,"C02 per GDP (t CO2\/yr)":0.230584423},{"EDGAR Country Code":"BRA","Country":"Brazil","year":"2021","C02 per capita (t CO2\/yr)":2.275465833,"total C02 emissions (Mt CO2\/yr)":489.8577336,"Cumulative CO\u2082 emissions (1970\u20132021 in Mt CO2)":16174.8412835,"C02 per GDP (t CO2\/yr)":0.156627975},{"EDGAR Country Code":"BRB","Country":"Barbados","year":"2021","C02 per capita (t CO2\/yr)":6.130127051,"total C02 emissions (Mt CO2\/yr)":1.765476591,"Cumulative CO\u2082 emissions (1970\u20132021 in Mt CO2)":77.281528408,"C02 per GDP (t CO2\/yr)":0.454979037},{"EDGAR Country Code":"BRN","Country":"Brunei","year":"2021","C02 per capita (t CO2\/yr)":16.05289658,"total C02 emissions (Mt CO2\/yr)":7.207750563,"Cumulative CO\u2082 emissions (1970\u20132021 in Mt CO2)":249.625562907,"C02 per GDP (t CO2\/yr)":0.269197734},{"EDGAR Country Code":"BTN","Country":"Bhutan","year":"2021","C02 per capita (t CO2\/yr)":2.340925764,"total C02 emissions (Mt CO2\/yr)":1.975741344,"Cumulative CO\u2082 emissions (1970\u20132021 in Mt CO2)":26.785506617,"C02 per GDP (t CO2\/yr)":0.251995396},{"EDGAR Country Code":"BWA","Country":"Botswana","year":"2021","C02 per capita (t CO2\/yr)":2.848901981,"total C02 emissions (Mt CO2\/yr)":6.999752167,"Cumulative CO\u2082 emissions (1970\u20132021 in Mt CO2)":171.238988363,"C02 per GDP (t CO2\/yr)":0.182223403},{"EDGAR Country Code":"CAF","Country":"Central African Republic","year":"2021","C02 per capita (t CO2\/yr)":0.054931304,"total C02 emissions (Mt CO2\/yr)":0.275919941,"Cumulative CO\u2082 emissions (1970\u20132021 in Mt CO2)":10.974994374,"C02 per GDP (t CO2\/yr)":0.060371176},{"EDGAR Country Code":"CAN","Country":"Canada","year":"2021","C02 per capita (t CO2\/yr)":14.8596767,"total C02 emissions (Mt CO2\/yr)":563.5383792,"Cumulative CO\u2082 emissions (1970\u20132021 in Mt CO2)":25832.6562331,"C02 per GDP (t CO2\/yr)":0.307590754},{"EDGAR Country Code":"CHE","Country":"Switzerland and Liechtenstein","year":"2021","C02 per capita (t CO2\/yr)":4.017016723,"total C02 emissions (Mt CO2\/yr)":35.07257301,"Cumulative CO\u2082 emissions (1970\u20132021 in Mt CO2)":2261.29899813,"C02 per GDP (t CO2\/yr)":0.056960507},{"EDGAR Country Code":"CHL","Country":"Chile","year":"2021","C02 per capita (t CO2\/yr)":4.606465291,"total C02 emissions (Mt CO2\/yr)":85.70328674,"Cumulative CO\u2082 emissions (1970\u20132021 in Mt CO2)":2561.95291724,"C02 per GDP (t CO2\/yr)":0.172759423},{"EDGAR Country Code":"CHN","Country":"China","year":"2021","C02 per capita (t CO2\/yr)":8.726979711,"total C02 emissions (Mt CO2\/yr)":12466.31598,"Cumulative CO\u2082 emissions (1970\u20132021 in Mt CO2)":253399.1442513,"C02 per GDP (t CO2\/yr)":0.501433715},{"EDGAR Country Code":"CIV","Country":"C\u00f4te d\u2019Ivoire","year":"2021","C02 per capita (t CO2\/yr)":0.542117615,"total C02 emissions (Mt CO2\/yr)":14.54393137,"Cumulative CO\u2082 emissions (1970\u20132021 in Mt CO2)":316.145561275,"C02 per GDP (t CO2\/yr)":0.099431664},{"EDGAR Country Code":"CMR","Country":"Cameroon","year":"2021","C02 per capita (t CO2\/yr)":0.383373202,"total C02 emissions (Mt CO2\/yr)":10.20271103,"Cumulative CO\u2082 emissions (1970\u20132021 in Mt CO2)":274.575209199,"C02 per GDP (t CO2\/yr)":0.101296282},{"EDGAR Country Code":"COD","Country":"Democratic Republic of the Congo","year":"2021","C02 per capita (t CO2\/yr)":0.036491709,"total C02 emissions (Mt CO2\/yr)":3.369498414,"Cumulative CO\u2082 emissions (1970\u20132021 in Mt CO2)":160.030553623,"C02 per GDP (t CO2\/yr)":0.032878599},{"EDGAR Country Code":"COG","Country":"Congo","year":"2021","C02 per capita (t CO2\/yr)":1.263460047,"total C02 emissions (Mt CO2\/yr)":7.371025916,"Cumulative CO\u2082 emissions (1970\u20132021 in Mt CO2)":214.841031587,"C02 per GDP (t CO2\/yr)":0.395772703},{"EDGAR Country Code":"COK","Country":"Cook Islands","year":"2021","C02 per capita (t CO2\/yr)":6.413230057,"total C02 emissions (Mt CO2\/yr)":0.109024911,"Cumulative CO\u2082 emissions (1970\u20132021 in Mt CO2)":2.931620394,"C02 per GDP (t CO2\/yr)":null},{"EDGAR Country Code":"COL","Country":"Colombia","year":"2021","C02 per capita (t CO2\/yr)":1.533737806,"total C02 emissions (Mt CO2\/yr)":77.57032327,"Cumulative CO\u2082 emissions (1970\u20132021 in Mt CO2)":2935.23371218,"C02 per GDP (t CO2\/yr)":0.102896193},{"EDGAR Country Code":"COM","Country":"Comoros","year":"2021","C02 per capita (t CO2\/yr)":0.313272737,"total C02 emissions (Mt CO2\/yr)":0.278186191,"Cumulative CO\u2082 emissions (1970\u20132021 in Mt CO2)":4.982800849,"C02 per GDP (t CO2\/yr)":0.104732393},{"EDGAR Country Code":"CPV","Country":"Cabo Verde","year":"2021","C02 per capita (t CO2\/yr)":1.594621714,"total C02 emissions (Mt CO2\/yr)":0.915312864,"Cumulative CO\u2082 emissions (1970\u20132021 in Mt CO2)":19.394262464,"C02 per GDP (t CO2\/yr)":0.254631856},{"EDGAR Country Code":"CRI","Country":"Costa Rica","year":"2021","C02 per capita (t CO2\/yr)":1.590128654,"total C02 emissions (Mt CO2\/yr)":8.090574591,"Cumulative CO\u2082 emissions (1970\u20132021 in Mt CO2)":248.042155491,"C02 per GDP (t CO2\/yr)":0.0740487},{"EDGAR Country Code":"CUB","Country":"Cuba","year":"2021","C02 per capita (t CO2\/yr)":2.139794786,"total C02 emissions (Mt CO2\/yr)":24.60550024,"Cumulative CO\u2082 emissions (1970\u20132021 in Mt CO2)":1490.95607586,"C02 per GDP (t CO2\/yr)":0.075340803},{"EDGAR Country Code":"CYM","Country":"Cayman Islands","year":"2021","C02 per capita (t CO2\/yr)":13.24144743,"total C02 emissions (Mt CO2\/yr)":0.860694083,"Cumulative CO\u2082 emissions (1970\u20132021 in Mt CO2)":22.644724256,"C02 per GDP (t CO2\/yr)":0.184137656},{"EDGAR Country Code":"CYP","Country":"Cyprus","year":"2021","C02 per capita (t CO2\/yr)":5.550617291,"total C02 emissions (Mt CO2\/yr)":6.749550626,"Cumulative CO\u2082 emissions (1970\u20132021 in Mt CO2)":279.272616644,"C02 per GDP (t CO2\/yr)":0.183845229},{"EDGAR Country Code":"CZE","Country":"Czechia","year":"2021","C02 per capita (t CO2\/yr)":9.186644194,"total C02 emissions (Mt CO2\/yr)":97.69077436,"Cumulative CO\u2082 emissions (1970\u20132021 in Mt CO2)":7704.81543277,"C02 per GDP (t CO2\/yr)":0.229450647},{"EDGAR Country Code":"DEU","Country":"Germany","year":"2021","C02 per capita (t CO2\/yr)":8.062521288,"total C02 emissions (Mt CO2\/yr)":665.8836332,"Cumulative CO\u2082 emissions (1970\u20132021 in Mt CO2)":49056.6885495,"C02 per GDP (t CO2\/yr)":0.15133374},{"EDGAR Country Code":"DJI","Country":"Djibouti","year":"2021","C02 per capita (t CO2\/yr)":0.600413399,"total C02 emissions (Mt CO2\/yr)":0.608819187,"Cumulative CO\u2082 emissions (1970\u20132021 in Mt CO2)":47.205218452,"C02 per GDP (t CO2\/yr)":0.112622771},{"EDGAR Country Code":"DMA","Country":"Dominica","year":"2021","C02 per capita (t CO2\/yr)":2.555652399,"total C02 emissions (Mt CO2\/yr)":0.194229582,"Cumulative CO\u2082 emissions (1970\u20132021 in Mt CO2)":8.556970047,"C02 per GDP (t CO2\/yr)":0.24691632},{"EDGAR Country Code":"DNK","Country":"Denmark","year":"2021","C02 per capita (t CO2\/yr)":4.688096639,"total C02 emissions (Mt CO2\/yr)":27.28003434,"Cumulative CO\u2082 emissions (1970\u20132021 in Mt CO2)":2797.44977191,"C02 per GDP (t CO2\/yr)":0.080050346},{"EDGAR Country Code":"DOM","Country":"Dominican Republic","year":"2021","C02 per capita (t CO2\/yr)":2.471614982,"total C02 emissions (Mt CO2\/yr)":27.72657687,"Cumulative CO\u2082 emissions (1970\u20132021 in Mt CO2)":734.44088278,"C02 per GDP (t CO2\/yr)":0.133891533},{"EDGAR Country Code":"DZA","Country":"Algeria","year":"2021","C02 per capita (t CO2\/yr)":3.934605075,"total C02 emissions (Mt CO2\/yr)":173.0006505,"Cumulative CO\u2082 emissions (1970\u20132021 in Mt CO2)":4638.70860129,"C02 per GDP (t CO2\/yr)":0.353877549},{"EDGAR Country Code":"ECU","Country":"Ecuador","year":"2021","C02 per capita (t CO2\/yr)":2.341795988,"total C02 emissions (Mt CO2\/yr)":41.14067192,"Cumulative CO\u2082 emissions (1970\u20132021 in Mt CO2)":1182.458742787,"C02 per GDP (t CO2\/yr)":0.216666975},{"EDGAR Country Code":"EGY","Country":"Egypt","year":"2021","C02 per capita (t CO2\/yr)":2.476992937,"total C02 emissions (Mt CO2\/yr)":259.3213445,"Cumulative CO\u2082 emissions (1970\u20132021 in Mt CO2)":6671.41241258,"C02 per GDP (t CO2\/yr)":0.205202836},{"EDGAR Country Code":"ERI","Country":"Eritrea","year":"2021","C02 per capita (t CO2\/yr)":0.150351019,"total C02 emissions (Mt CO2\/yr)":0.835199911,"Cumulative CO\u2082 emissions (1970\u20132021 in Mt CO2)":27.039893313,"C02 per GDP (t CO2\/yr)":0.053985031},{"EDGAR Country Code":"ESH","Country":"Western Sahara","year":"2021","C02 per capita (t CO2\/yr)":0.390055004,"total C02 emissions (Mt CO2\/yr)":0.238713663,"Cumulative CO\u2082 emissions (1970\u20132021 in Mt CO2)":9.393414975,"C02 per GDP (t CO2\/yr)":null},{"EDGAR Country Code":"ESP","Country":"Spain and Andorra","year":"2021","C02 per capita (t CO2\/yr)":4.992878803,"total C02 emissions (Mt CO2\/yr)":231.9142275,"Cumulative CO\u2082 emissions (1970\u20132021 in Mt CO2)":13032.8513934,"C02 per GDP (t CO2\/yr)":0.128623675},{"EDGAR Country Code":"EST","Country":"Estonia","year":"2021","C02 per capita (t CO2\/yr)":11.49241997,"total C02 emissions (Mt CO2\/yr)":14.9056687,"Cumulative CO\u2082 emissions (1970\u20132021 in Mt CO2)":1289.4468896,"C02 per GDP (t CO2\/yr)":0.293491755},{"EDGAR Country Code":"ETH","Country":"Ethiopia","year":"2021","C02 per capita (t CO2\/yr)":0.166448638,"total C02 emissions (Mt CO2\/yr)":19.20883863,"Cumulative CO\u2082 emissions (1970\u20132021 in Mt CO2)":274.204862226,"C02 per GDP (t CO2\/yr)":0.068862571},{"EDGAR Country Code":"FIN","Country":"Finland","year":"2021","C02 per capita (t CO2\/yr)":6.965433631,"total C02 emissions (Mt CO2\/yr)":38.99249746,"Cumulative CO\u2082 emissions (1970\u20132021 in Mt CO2)":2855.34917798,"C02 per GDP (t CO2\/yr)":0.143781692},{"EDGAR Country Code":"FJI","Country":"Fiji","year":"2021","C02 per capita (t CO2\/yr)":1.861727822,"total C02 emissions (Mt CO2\/yr)":1.731406874,"Cumulative CO\u2082 emissions (1970\u20132021 in Mt CO2)":63.057497555,"C02 per GDP (t CO2\/yr)":0.174686113},{"EDGAR Country Code":"FLK","Country":"Falkland Islands","year":"2021","C02 per capita (t CO2\/yr)":18.1052976,"total C02 emissions (Mt CO2\/yr)":0.054315893,"Cumulative CO\u2082 emissions (1970\u20132021 in Mt CO2)":4.423877865,"C02 per GDP (t CO2\/yr)":null},{"EDGAR Country Code":"FRA","Country":"France and Monaco","year":"2021","C02 per capita (t CO2\/yr)":4.583838597,"total C02 emissions (Mt CO2\/yr)":302.3270747,"Cumulative CO\u2082 emissions (1970\u20132021 in Mt CO2)":21127.8050124,"C02 per GDP (t CO2\/yr)":0.099119636},{"EDGAR Country Code":"FRO","Country":"Faroes","year":"2021","C02 per capita (t CO2\/yr)":0.039572175,"total C02 emissions (Mt CO2\/yr)":0.001978609,"Cumulative CO\u2082 emissions (1970\u20132021 in Mt CO2)":0.079387026,"C02 per GDP (t CO2\/yr)":null},{"EDGAR Country Code":"GAB","Country":"Gabon","year":"2021","C02 per capita (t CO2\/yr)":2.516157213,"total C02 emissions (Mt CO2\/yr)":5.520448926,"Cumulative CO\u2082 emissions (1970\u20132021 in Mt CO2)":292.633843993,"C02 per GDP (t CO2\/yr)":0.1706258},{"EDGAR Country Code":"GBR","Country":"United Kingdom","year":"2021","C02 per capita (t CO2\/yr)":4.953739174,"total C02 emissions (Mt CO2\/yr)":335.3631883,"Cumulative CO\u2082 emissions (1970\u20132021 in Mt CO2)":28568.8874321,"C02 per GDP (t CO2\/yr)":0.108665659},{"EDGAR Country Code":"GEO","Country":"Georgia","year":"2021","C02 per capita (t CO2\/yr)":2.996198632,"total C02 emissions (Mt CO2\/yr)":11.64922028,"Cumulative CO\u2082 emissions (1970\u20132021 in Mt CO2)":971.401189281,"C02 per GDP (t CO2\/yr)":0.203023932},{"EDGAR Country Code":"GHA","Country":"Ghana","year":"2021","C02 per capita (t CO2\/yr)":0.753347812,"total C02 emissions (Mt CO2\/yr)":23.63553424,"Cumulative CO\u2082 emissions (1970\u20132021 in Mt CO2)":379.890761792,"C02 per GDP (t CO2\/yr)":0.132445103},{"EDGAR Country Code":"GIB","Country":"Gibraltar","year":"2021","C02 per capita (t CO2\/yr)":19.13418738,"total C02 emissions (Mt CO2\/yr)":0.669696558,"Cumulative CO\u2082 emissions (1970\u20132021 in Mt CO2)":15.309883166,"C02 per GDP (t CO2\/yr)":0.228487457},{"EDGAR Country Code":"GIN","Country":"Guinea","year":"2021","C02 per capita (t CO2\/yr)":0.243851747,"total C02 emissions (Mt CO2\/yr)":3.440748151,"Cumulative CO\u2082 emissions (1970\u20132021 in Mt CO2)":79.403795032,"C02 per GDP (t CO2\/yr)":0.097289363},{"EDGAR Country Code":"GLP","Country":"Guadeloupe","year":"2021","C02 per capita (t CO2\/yr)":4.0294905,"total C02 emissions (Mt CO2\/yr)":1.805211744,"Cumulative CO\u2082 emissions (1970\u20132021 in Mt CO2)":78.360581632,"C02 per GDP (t CO2\/yr)":null},{"EDGAR Country Code":"GMB","Country":"The Gambia","year":"2021","C02 per capita (t CO2\/yr)":0.236297493,"total C02 emissions (Mt CO2\/yr)":0.557662085,"Cumulative CO\u2082 emissions (1970\u20132021 in Mt CO2)":13.985157609,"C02 per GDP (t CO2\/yr)":0.101214215},{"EDGAR Country Code":"GNB","Country":"Guinea-Bissau","year":"2021","C02 per capita (t CO2\/yr)":0.15670427,"total C02 emissions (Mt CO2\/yr)":0.320930346,"Cumulative CO\u2082 emissions (1970\u20132021 in Mt CO2)":10.987947979,"C02 per GDP (t CO2\/yr)":0.085037866},{"EDGAR Country Code":"GNQ","Country":"Equatorial Guinea","year":"2021","C02 per capita (t CO2\/yr)":4.823458692,"total C02 emissions (Mt CO2\/yr)":7.003662021,"Cumulative CO\u2082 emissions (1970\u20132021 in Mt CO2)":189.180493939,"C02 per GDP (t CO2\/yr)":0.292750096},{"EDGAR Country Code":"GRC","Country":"Greece","year":"2021","C02 per capita (t CO2\/yr)":4.819185173,"total C02 emissions (Mt CO2\/yr)":53.37247579,"Cumulative CO\u2082 emissions (1970\u20132021 in Mt CO2)":3760.44205931,"C02 per GDP (t CO2\/yr)":0.170062098},{"EDGAR Country Code":"GRD","Country":"Grenada","year":"2021","C02 per capita (t CO2\/yr)":3.155057198,"total C02 emissions (Mt CO2\/yr)":0.343901235,"Cumulative CO\u2082 emissions (1970\u20132021 in Mt CO2)":12.236988556,"C02 per GDP (t CO2\/yr)":0.200414166},{"EDGAR Country Code":"GRL","Country":"Greenland","year":"2021","C02 per capita (t CO2\/yr)":8.14944685,"total C02 emissions (Mt CO2\/yr)":0.46451847,"Cumulative CO\u2082 emissions (1970\u20132021 in Mt CO2)":10.229546014,"C02 per GDP (t CO2\/yr)":0.001707308},{"EDGAR Country Code":"GTM","Country":"Guatemala","year":"2021","C02 per capita (t CO2\/yr)":1.106726636,"total C02 emissions (Mt CO2\/yr)":20.19112075,"Cumulative CO\u2082 emissions (1970\u20132021 in Mt CO2)":436.818914348,"C02 per GDP (t CO2\/yr)":0.132706986},{"EDGAR Country Code":"GUF","Country":"French Guiana","year":"2021","C02 per capita (t CO2\/yr)":2.699154604,"total C02 emissions (Mt CO2\/yr)":0.839437082,"Cumulative CO\u2082 emissions (1970\u20132021 in Mt CO2)":32.439281236,"C02 per GDP (t CO2\/yr)":null},{"EDGAR Country Code":"GUY","Country":"Guyana","year":"2021","C02 per capita (t CO2\/yr)":3.648109062,"total C02 emissions (Mt CO2\/yr)":2.900246704,"Cumulative CO\u2082 emissions (1970\u20132021 in Mt CO2)":89.257537027,"C02 per GDP (t CO2\/yr)":0.164592485},{"EDGAR Country Code":"HKG","Country":"Hong Kong","year":"2021","C02 per capita (t CO2\/yr)":4.370229822,"total C02 emissions (Mt CO2\/yr)":33.20500618,"Cumulative CO\u2082 emissions (1970\u20132021 in Mt CO2)":1699.237645701,"C02 per GDP (t CO2\/yr)":0.074589553},{"EDGAR Country Code":"HND","Country":"Honduras","year":"2021","C02 per capita (t CO2\/yr)":0.988030125,"total C02 emissions (Mt CO2\/yr)":9.750869303,"Cumulative CO\u2082 emissions (1970\u20132021 in Mt CO2)":256.2518664,"C02 per GDP (t CO2\/yr)":0.170253184},{"EDGAR Country Code":"HRV","Country":"Croatia","year":"2021","C02 per capita (t CO2\/yr)":4.397397585,"total C02 emissions (Mt CO2\/yr)":17.99854832,"Cumulative CO\u2082 emissions (1970\u20132021 in Mt CO2)":1183.05300283,"C02 per GDP (t CO2\/yr)":0.148685909},{"EDGAR Country Code":"HTI","Country":"Haiti","year":"2021","C02 per capita (t CO2\/yr)":0.282111797,"total C02 emissions (Mt CO2\/yr)":3.243721444,"Cumulative CO\u2082 emissions (1970\u20132021 in Mt CO2)":85.555238973,"C02 per GDP (t CO2\/yr)":0.09872484},{"EDGAR Country Code":"HUN","Country":"Hungary","year":"2021","C02 per capita (t CO2\/yr)":5.287501623,"total C02 emissions (Mt CO2\/yr)":50.69127806,"Cumulative CO\u2082 emissions (1970\u20132021 in Mt CO2)":3474.32394061,"C02 per GDP (t CO2\/yr)":0.155754767},{"EDGAR Country Code":"IDN","Country":"Indonesia","year":"2021","C02 per capita (t CO2\/yr)":2.19241382,"total C02 emissions (Mt CO2\/yr)":602.593708,"Cumulative CO\u2082 emissions (1970\u20132021 in Mt CO2)":13916.28654904,"C02 per GDP (t CO2\/yr)":0.185630182},{"EDGAR Country Code":"IND","Country":"India","year":"2021","C02 per capita (t CO2\/yr)":1.895474121,"total C02 emissions (Mt CO2\/yr)":2648.779133,"Cumulative CO\u2082 emissions (1970\u20132021 in Mt CO2)":53939.2487967,"C02 per GDP (t CO2\/yr)":0.284769268},{"EDGAR Country Code":"IRL","Country":"Ireland","year":"2021","C02 per capita (t CO2\/yr)":7.10782627,"total C02 emissions (Mt CO2\/yr)":35.01315221,"Cumulative CO\u2082 emissions (1970\u20132021 in Mt CO2)":1803.01451193,"C02 per GDP (t CO2\/yr)":0.068164594},{"EDGAR Country Code":"IRN","Country":"Iran","year":"2021","C02 per capita (t CO2\/yr)":8.431354259,"total C02 emissions (Mt CO2\/yr)":710.8306148,"Cumulative CO\u2082 emissions (1970\u20132021 in Mt CO2)":17639.329307,"C02 per GDP (t CO2\/yr)":0.543540453},{"EDGAR Country Code":"IRQ","Country":"Iraq","year":"2021","C02 per capita (t CO2\/yr)":4.173679259,"total C02 emissions (Mt CO2\/yr)":177.8488206,"Cumulative CO\u2082 emissions (1970\u20132021 in Mt CO2)":4485.38187748,"C02 per GDP (t CO2\/yr)":0.455829521},{"EDGAR Country Code":"ISL","Country":"Iceland","year":"2021","C02 per capita (t CO2\/yr)":8.404638118,"total C02 emissions (Mt CO2\/yr)":2.908004789,"Cumulative CO\u2082 emissions (1970\u20132021 in Mt CO2)":144.603798371,"C02 per GDP (t CO2\/yr)":0.146102422},{"EDGAR Country Code":"ISR","Country":"Israel and Palestine, State of","year":"2021","C02 per capita (t CO2\/yr)":6.739385167,"total C02 emissions (Mt CO2\/yr)":59.58964365,"Cumulative CO\u2082 emissions (1970\u20132021 in Mt CO2)":2347.96673777,"C02 per GDP (t CO2\/yr)":0.102746135},{"EDGAR Country Code":"ITA","Country":"Italy, San Marino and the Holy See","year":"2021","C02 per capita (t CO2\/yr)":5.414631447,"total C02 emissions (Mt CO2\/yr)":319.6690114,"Cumulative CO\u2082 emissions (1970\u20132021 in Mt CO2)":20934.3977228,"C02 per GDP (t CO2\/yr)":0.129051119},{"EDGAR Country Code":"JAM","Country":"Jamaica","year":"2021","C02 per capita (t CO2\/yr)":2.768424663,"total C02 emissions (Mt CO2\/yr)":8.081031591,"Cumulative CO\u2082 emissions (1970\u20132021 in Mt CO2)":418.274851979,"C02 per GDP (t CO2\/yr)":0.297795725},{"EDGAR Country Code":"JOR","Country":"Jordan","year":"2021","C02 per capita (t CO2\/yr)":2.354339576,"total C02 emissions (Mt CO2\/yr)":24.29678442,"Cumulative CO\u2082 emissions (1970\u20132021 in Mt CO2)":741.258769532,"C02 per GDP (t CO2\/yr)":0.237335926},{"EDGAR Country Code":"JPN","Country":"Japan","year":"2021","C02 per capita (t CO2\/yr)":8.601217929,"total C02 emissions (Mt CO2\/yr)":1084.690992,"Cumulative CO\u2082 emissions (1970\u20132021 in Mt CO2)":58977.8735739,"C02 per GDP (t CO2\/yr)":0.211687628},{"EDGAR Country Code":"KAZ","Country":"Kazakhstan","year":"2021","C02 per capita (t CO2\/yr)":11.14139098,"total C02 emissions (Mt CO2\/yr)":211.2073488,"Cumulative CO\u2082 emissions (1970\u20132021 in Mt CO2)":10712.6798594,"C02 per GDP (t CO2\/yr)":0.426941255},{"EDGAR Country Code":"KEN","Country":"Kenya","year":"2021","C02 per capita (t CO2\/yr)":0.40945331,"total C02 emissions (Mt CO2\/yr)":22.43026178,"Cumulative CO\u2082 emissions (1970\u20132021 in Mt CO2)":468.292317084,"C02 per GDP (t CO2\/yr)":0.089210261},{"EDGAR Country Code":"KGZ","Country":"Kyrgyzstan","year":"2021","C02 per capita (t CO2\/yr)":1.689098343,"total C02 emissions (Mt CO2\/yr)":10.77982562,"Cumulative CO\u2082 emissions (1970\u20132021 in Mt CO2)":674.254160841,"C02 per GDP (t CO2\/yr)":0.334561853},{"EDGAR Country Code":"KHM","Country":"Cambodia","year":"2021","C02 per capita (t CO2\/yr)":1.000650531,"total C02 emissions (Mt CO2\/yr)":16.9550226,"Cumulative CO\u2082 emissions (1970\u20132021 in Mt CO2)":169.959741837,"C02 per GDP (t CO2\/yr)":0.234710633},{"EDGAR Country Code":"KIR","Country":"Kiribati","year":"2021","C02 per capita (t CO2\/yr)":0.606166308,"total C02 emissions (Mt CO2\/yr)":0.075164622,"Cumulative CO\u2082 emissions (1970\u20132021 in Mt CO2)":1.924824027,"C02 per GDP (t CO2\/yr)":0.301091412},{"EDGAR Country Code":"KNA","Country":"Saint Kitts and Nevis","year":"2021","C02 per capita (t CO2\/yr)":4.93731283,"total C02 emissions (Mt CO2\/yr)":0.286364144,"Cumulative CO\u2082 emissions (1970\u20132021 in Mt CO2)":10.457050486,"C02 per GDP (t CO2\/yr)":0.223766865},{"EDGAR Country Code":"KOR","Country":"South Korea","year":"2021","C02 per capita (t CO2\/yr)":12.13153523,"total C02 emissions (Mt CO2\/yr)":626.8000309,"Cumulative CO\u2082 emissions (1970\u20132021 in Mt CO2)":19289.4601865,"C02 per GDP (t CO2\/yr)":0.274577786},{"EDGAR Country Code":"KWT","Country":"Kuwait","year":"2021","C02 per capita (t CO2\/yr)":22.49093916,"total C02 emissions (Mt CO2\/yr)":98.08298568,"Cumulative CO\u2082 emissions (1970\u20132021 in Mt CO2)":2957.62683514,"C02 per GDP (t CO2\/yr)":0.50555124},{"EDGAR Country Code":"LAO","Country":"Laos","year":"2021","C02 per capita (t CO2\/yr)":2.830724914,"total C02 emissions (Mt CO2\/yr)":20.55955505,"Cumulative CO\u2082 emissions (1970\u20132021 in Mt CO2)":166.876280799,"C02 per GDP (t CO2\/yr)":0.352867491},{"EDGAR Country Code":"LBN","Country":"Lebanon","year":"2021","C02 per capita (t CO2\/yr)":4.325094157,"total C02 emissions (Mt CO2\/yr)":25.76891099,"Cumulative CO\u2082 emissions (1970\u20132021 in Mt CO2)":728.371352653,"C02 per GDP (t CO2\/yr)":0.391176188},{"EDGAR Country Code":"LBR","Country":"Liberia","year":"2021","C02 per capita (t CO2\/yr)":0.27589823,"total C02 emissions (Mt CO2\/yr)":1.443499541,"Cumulative CO\u2082 emissions (1970\u20132021 in Mt CO2)":48.13972723,"C02 per GDP (t CO2\/yr)":0.197146711},{"EDGAR Country Code":"LBY","Country":"Libya","year":"2021","C02 per capita (t CO2\/yr)":9.380094681,"total C02 emissions (Mt CO2\/yr)":63.27811872,"Cumulative CO\u2082 emissions (1970\u20132021 in Mt CO2)":2150.59045072,"C02 per GDP (t CO2\/yr)":0.427723846},{"EDGAR Country Code":"LCA","Country":"Saint Lucia","year":"2021","C02 per capita (t CO2\/yr)":3.940755619,"total C02 emissions (Mt CO2\/yr)":0.713276767,"Cumulative CO\u2082 emissions (1970\u20132021 in Mt CO2)":17.983060669,"C02 per GDP (t CO2\/yr)":0.302422393},{"EDGAR Country Code":"LKA","Country":"Sri Lanka","year":"2021","C02 per capita (t CO2\/yr)":1.128464633,"total C02 emissions (Mt CO2\/yr)":23.86251312,"Cumulative CO\u2082 emissions (1970\u20132021 in Mt CO2)":525.329550583,"C02 per GDP (t CO2\/yr)":0.083754087},{"EDGAR Country Code":"LSO","Country":"Lesotho","year":"2021","C02 per capita (t CO2\/yr)":0.277561877,"total C02 emissions (Mt CO2\/yr)":0.652547973,"Cumulative CO\u2082 emissions (1970\u20132021 in Mt CO2)":15.601527395,"C02 per GDP (t CO2\/yr)":0.12379042},{"EDGAR Country Code":"LTU","Country":"Lithuania","year":"2021","C02 per capita (t CO2\/yr)":4.867899784,"total C02 emissions (Mt CO2\/yr)":13.82483539,"Cumulative CO\u2082 emissions (1970\u20132021 in Mt CO2)":1090.8455463,"C02 per GDP (t CO2\/yr)":0.126950887},{"EDGAR Country Code":"LUX","Country":"Luxembourg","year":"2021","C02 per capita (t CO2\/yr)":13.82394566,"total C02 emissions (Mt CO2\/yr)":8.446430798,"Cumulative CO\u2082 emissions (1970\u20132021 in Mt CO2)":595.88207275,"C02 per GDP (t CO2\/yr)":0.111364584},{"EDGAR Country Code":"LVA","Country":"Latvia","year":"2021","C02 per capita (t CO2\/yr)":3.846408959,"total C02 emissions (Mt CO2\/yr)":7.212016798,"Cumulative CO\u2082 emissions (1970\u20132021 in Mt CO2)":667.759129782,"C02 per GDP (t CO2\/yr)":0.120855662},{"EDGAR Country Code":"MAC","Country":"Macao","year":"2021","C02 per capita (t CO2\/yr)":4.014847597,"total C02 emissions (Mt CO2\/yr)":2.657829109,"Cumulative CO\u2082 emissions (1970\u20132021 in Mt CO2)":68.575505161,"C02 per GDP (t CO2\/yr)":0.060091256},{"EDGAR Country Code":"MAR","Country":"Morocco","year":"2021","C02 per capita (t CO2\/yr)":1.972586681,"total C02 emissions (Mt CO2\/yr)":73.96805538,"Cumulative CO\u2082 emissions (1970\u20132021 in Mt CO2)":1742.438294242,"C02 per GDP (t CO2\/yr)":0.262894437},{"EDGAR Country Code":"MDA","Country":"Moldova","year":"2021","C02 per capita (t CO2\/yr)":2.384440344,"total C02 emissions (Mt CO2\/yr)":9.549683576,"Cumulative CO\u2082 emissions (1970\u20132021 in Mt CO2)":844.545621842,"C02 per GDP (t CO2\/yr)":0.260657423},{"EDGAR Country Code":"MDG","Country":"Madagascar","year":"2021","C02 per capita (t CO2\/yr)":0.186440898,"total C02 emissions (Mt CO2\/yr)":5.299768977,"Cumulative CO\u2082 emissions (1970\u20132021 in Mt CO2)":102.216087323,"C02 per GDP (t CO2\/yr)":0.125236138},{"EDGAR Country Code":"MDV","Country":"Maldives","year":"2021","C02 per capita (t CO2\/yr)":4.744874214,"total C02 emissions (Mt CO2\/yr)":2.206366509,"Cumulative CO\u2082 emissions (1970\u20132021 in Mt CO2)":30.867918617,"C02 per GDP (t CO2\/yr)":0.244556782},{"EDGAR Country Code":"MEX","Country":"Mexico","year":"2021","C02 per capita (t CO2\/yr)":3.090084051,"total C02 emissions (Mt CO2\/yr)":418.3479391,"Cumulative CO\u2082 emissions (1970\u20132021 in Mt CO2)":17828.4291233,"C02 per GDP (t CO2\/yr)":0.17318053},{"EDGAR Country Code":"MKD","Country":"North Macedonia","year":"2021","C02 per capita (t CO2\/yr)":3.593943158,"total C02 emissions (Mt CO2\/yr)":7.507747257,"Cumulative CO\u2082 emissions (1970\u20132021 in Mt CO2)":491.059067928,"C02 per GDP (t CO2\/yr)":0.220813701},{"EDGAR Country Code":"MLI","Country":"Mali","year":"2021","C02 per capita (t CO2\/yr)":0.283444191,"total C02 emissions (Mt CO2\/yr)":5.921716039,"Cumulative CO\u2082 emissions (1970\u20132021 in Mt CO2)":71.17935591,"C02 per GDP (t CO2\/yr)":0.127458385},{"EDGAR Country Code":"MLT","Country":"Malta","year":"2021","C02 per capita (t CO2\/yr)":4.00328589,"total C02 emissions (Mt CO2\/yr)":1.745432648,"Cumulative CO\u2082 emissions (1970\u20132021 in Mt CO2)":98.215119507,"C02 per GDP (t CO2\/yr)":0.076065078},{"EDGAR Country Code":"MMR","Country":"Myanmar\/Burma","year":"2021","C02 per capita (t CO2\/yr)":0.724649267,"total C02 emissions (Mt CO2\/yr)":40.05064036,"Cumulative CO\u2082 emissions (1970\u20132021 in Mt CO2)":556.723939668,"C02 per GDP (t CO2\/yr)":0.184771409},{"EDGAR Country Code":"MNG","Country":"Mongolia","year":"2021","C02 per capita (t CO2\/yr)":7.685402155,"total C02 emissions (Mt CO2\/yr)":24.98524241,"Cumulative CO\u2082 emissions (1970\u20132021 in Mt CO2)":635.39853739,"C02 per GDP (t CO2\/yr)":0.640968788},{"EDGAR Country Code":"MOZ","Country":"Mozambique","year":"2021","C02 per capita (t CO2\/yr)":0.260136592,"total C02 emissions (Mt CO2\/yr)":8.644338953,"Cumulative CO\u2082 emissions (1970\u20132021 in Mt CO2)":165.023912973,"C02 per GDP (t CO2\/yr)":0.219971217},{"EDGAR Country Code":"MRT","Country":"Mauritania","year":"2021","C02 per capita (t CO2\/yr)":0.867330651,"total C02 emissions (Mt CO2\/yr)":4.256858833,"Cumulative CO\u2082 emissions (1970\u20132021 in Mt CO2)":88.485478637,"C02 per GDP (t CO2\/yr)":0.175141539},{"EDGAR Country Code":"MTQ","Country":"Martinique","year":"2021","C02 per capita (t CO2\/yr)":4.93367756,"total C02 emissions (Mt CO2\/yr)":1.904399538,"Cumulative CO\u2082 emissions (1970\u20132021 in Mt CO2)":82.756417471,"C02 per GDP (t CO2\/yr)":null},{"EDGAR Country Code":"MUS","Country":"Mauritius","year":"2021","C02 per capita (t CO2\/yr)":3.235055369,"total C02 emissions (Mt CO2\/yr)":4.12793065,"Cumulative CO\u2082 emissions (1970\u20132021 in Mt CO2)":105.040030916,"C02 per GDP (t CO2\/yr)":0.161056519},{"EDGAR Country Code":"MWI","Country":"Malawi","year":"2021","C02 per capita (t CO2\/yr)":0.087199927,"total C02 emissions (Mt CO2\/yr)":1.818903274,"Cumulative CO\u2082 emissions (1970\u20132021 in Mt CO2)":57.604720357,"C02 per GDP (t CO2\/yr)":0.061328708},{"EDGAR Country Code":"MYS","Country":"Malaysia","year":"2021","C02 per capita (t CO2\/yr)":7.556706881,"total C02 emissions (Mt CO2\/yr)":251.5552154,"Cumulative CO\u2082 emissions (1970\u20132021 in Mt CO2)":6120.42109177,"C02 per GDP (t CO2\/yr)":0.284686581},{"EDGAR Country Code":"NAM","Country":"Namibia","year":"2021","C02 per capita (t CO2\/yr)":1.47778437,"total C02 emissions (Mt CO2\/yr)":4.065384801,"Cumulative CO\u2082 emissions (1970\u20132021 in Mt CO2)":112.258350855,"C02 per GDP (t CO2\/yr)":0.176047335},{"EDGAR Country Code":"NCL","Country":"New Caledonia","year":"2021","C02 per capita (t CO2\/yr)":19.58450792,"total C02 emissions (Mt CO2\/yr)":5.699091806,"Cumulative CO\u2082 emissions (1970\u20132021 in Mt CO2)":126.298985435,"C02 per GDP (t CO2\/yr)":0.624112559},{"EDGAR Country Code":"NER","Country":"Niger","year":"2021","C02 per capita (t CO2\/yr)":0.098768895,"total C02 emissions (Mt CO2\/yr)":2.469814991,"Cumulative CO\u2082 emissions (1970\u20132021 in Mt CO2)":48.978380787,"C02 per GDP (t CO2\/yr)":0.082430088},{"EDGAR Country Code":"NGA","Country":"Nigeria","year":"2021","C02 per capita (t CO2\/yr)":0.600761665,"total C02 emissions (Mt CO2\/yr)":127.0292518,"Cumulative CO\u2082 emissions (1970\u20132021 in Mt CO2)":4574.26725345,"C02 per GDP (t CO2\/yr)":0.120923086},{"EDGAR Country Code":"NIC","Country":"Nicaragua","year":"2021","C02 per capita (t CO2\/yr)":0.771861518,"total C02 emissions (Mt CO2\/yr)":5.002434496,"Cumulative CO\u2082 emissions (1970\u20132021 in Mt CO2)":172.724276266,"C02 per GDP (t CO2\/yr)":0.129500548},{"EDGAR Country Code":"NLD","Country":"Netherlands","year":"2021","C02 per capita (t CO2\/yr)":8.523977652,"total C02 emissions (Mt CO2\/yr)":146.8681349,"Cumulative CO\u2082 emissions (1970\u20132021 in Mt CO2)":8541.5110412,"C02 per GDP (t CO2\/yr)":0.147574447},{"EDGAR Country Code":"NOR","Country":"Norway","year":"2021","C02 per capita (t CO2\/yr)":7.696220227,"total C02 emissions (Mt CO2\/yr)":42.32921125,"Cumulative CO\u2082 emissions (1970\u20132021 in Mt CO2)":2161.00714881,"C02 per GDP (t CO2\/yr)":0.119148372},{"EDGAR Country Code":"NPL","Country":"Nepal","year":"2021","C02 per capita (t CO2\/yr)":0.468105997,"total C02 emissions (Mt CO2\/yr)":14.31374519,"Cumulative CO\u2082 emissions (1970\u20132021 in Mt CO2)":181.798720782,"C02 per GDP (t CO2\/yr)":0.124367285},{"EDGAR Country Code":"NZL","Country":"New Zealand","year":"2021","C02 per capita (t CO2\/yr)":6.687864235,"total C02 emissions (Mt CO2\/yr)":32.60333814,"Cumulative CO\u2082 emissions (1970\u20132021 in Mt CO2)":1441.91651126,"C02 per GDP (t CO2\/yr)":0.146983765},{"EDGAR Country Code":"OMN","Country":"Oman","year":"2021","C02 per capita (t CO2\/yr)":17.95439722,"total C02 emissions (Mt CO2\/yr)":94.61967335,"Cumulative CO\u2082 emissions (1970\u20132021 in Mt CO2)":1756.590936696,"C02 per GDP (t CO2\/yr)":0.615736961},{"EDGAR Country Code":"PAK","Country":"Pakistan","year":"2021","C02 per capita (t CO2\/yr)":1.036233816,"total C02 emissions (Mt CO2\/yr)":219.7924461,"Cumulative CO\u2082 emissions (1970\u20132021 in Mt CO2)":5019.76415764,"C02 per GDP (t CO2\/yr)":0.182422735},{"EDGAR Country Code":"PAN","Country":"Panama","year":"2021","C02 per capita (t CO2\/yr)":2.874745713,"total C02 emissions (Mt CO2\/yr)":12.51089334,"Cumulative CO\u2082 emissions (1970\u20132021 in Mt CO2)":297.277571234,"C02 per GDP (t CO2\/yr)":0.099016411},{"EDGAR Country Code":"PER","Country":"Peru","year":"2021","C02 per capita (t CO2\/yr)":1.637012117,"total C02 emissions (Mt CO2\/yr)":55.14439017,"Cumulative CO\u2082 emissions (1970\u20132021 in Mt CO2)":1609.26517425,"C02 per GDP (t CO2\/yr)":0.130693308},{"EDGAR Country Code":"PHL","Country":"Philippines","year":"2021","C02 per capita (t CO2\/yr)":1.329304894,"total C02 emissions (Mt CO2\/yr)":147.9556226,"Cumulative CO\u2082 emissions (1970\u20132021 in Mt CO2)":3487.62276544,"C02 per GDP (t CO2\/yr)":0.160502715},{"EDGAR Country Code":"PLW","Country":"Palau","year":"2021","C02 per capita (t CO2\/yr)":60.16816353,"total C02 emissions (Mt CO2\/yr)":1.323699598,"Cumulative CO\u2082 emissions (1970\u20132021 in Mt CO2)":100.946532664,"C02 per GDP (t CO2\/yr)":5.704522362},{"EDGAR Country Code":"PNG","Country":"Papua New Guinea","year":"2021","C02 per capita (t CO2\/yr)":0.736111372,"total C02 emissions (Mt CO2\/yr)":6.570530106,"Cumulative CO\u2082 emissions (1970\u20132021 in Mt CO2)":170.56897808,"C02 per GDP (t CO2\/yr)":0.178066891},{"EDGAR Country Code":"POL","Country":"Poland","year":"2021","C02 per capita (t CO2\/yr)":8.475616691,"total C02 emissions (Mt CO2\/yr)":320.7681893,"Cumulative CO\u2082 emissions (1970\u20132021 in Mt CO2)":18809.4406305,"C02 per GDP (t CO2\/yr)":0.24707355},{"EDGAR Country Code":"PRI","Country":"Puerto Rico","year":"2021","C02 per capita (t CO2\/yr)":0.345844837,"total C02 emissions (Mt CO2\/yr)":1.260950276,"Cumulative CO\u2082 emissions (1970\u20132021 in Mt CO2)":86.337608923,"C02 per GDP (t CO2\/yr)":0.01168783},{"EDGAR Country Code":"PRK","Country":"North Korea","year":"2021","C02 per capita (t CO2\/yr)":2.411221138,"total C02 emissions (Mt CO2\/yr)":62.57359975,"Cumulative CO\u2082 emissions (1970\u20132021 in Mt CO2)":4440.11833265,"C02 per GDP (t CO2\/yr)":0.511056134},{"EDGAR Country Code":"PRT","Country":"Portugal","year":"2021","C02 per capita (t CO2\/yr)":3.798183942,"total C02 emissions (Mt CO2\/yr)":38.67690709,"Cumulative CO\u2082 emissions (1970\u20132021 in Mt CO2)":2275.28322033,"C02 per GDP (t CO2\/yr)":0.112049268},{"EDGAR Country Code":"PRY","Country":"Paraguay","year":"2021","C02 per capita (t CO2\/yr)":1.243689195,"total C02 emissions (Mt CO2\/yr)":8.891134056,"Cumulative CO\u2082 emissions (1970\u20132021 in Mt CO2)":189.617206135,"C02 per GDP (t CO2\/yr)":0.096805647},{"EDGAR Country Code":"PYF","Country":"French Polynesia","year":"2021","C02 per capita (t CO2\/yr)":3.321568115,"total C02 emissions (Mt CO2\/yr)":0.973219458,"Cumulative CO\u2082 emissions (1970\u20132021 in Mt CO2)":36.362117668,"C02 per GDP (t CO2\/yr)":0.185236829},{"EDGAR Country Code":"QAT","Country":"Qatar","year":"2021","C02 per capita (t CO2\/yr)":34.39925157,"total C02 emissions (Mt CO2\/yr)":97.69387446,"Cumulative CO\u2082 emissions (1970\u20132021 in Mt CO2)":2129.39866439,"C02 per GDP (t CO2\/yr)":0.391605227},{"EDGAR Country Code":"REU","Country":"R\u00e9union","year":"2021","C02 per capita (t CO2\/yr)":2.856397534,"total C02 emissions (Mt CO2\/yr)":2.579326973,"Cumulative CO\u2082 emissions (1970\u20132021 in Mt CO2)":86.240737641,"C02 per GDP (t CO2\/yr)":null},{"EDGAR Country Code":"ROU","Country":"Romania","year":"2021","C02 per capita (t CO2\/yr)":4.081197169,"total C02 emissions (Mt CO2\/yr)":78.74669937,"Cumulative CO\u2082 emissions (1970\u20132021 in Mt CO2)":6975.6854517,"C02 per GDP (t CO2\/yr)":0.133516277},{"EDGAR Country Code":"RUS","Country":"Russia","year":"2021","C02 per capita (t CO2\/yr)":13.52401366,"total C02 emissions (Mt CO2\/yr)":1942.535227,"Cumulative CO\u2082 emissions (1970\u20132021 in Mt CO2)":96633.628129,"C02 per GDP (t CO2\/yr)":0.476077164},{"EDGAR Country Code":"RWA","Country":"Rwanda","year":"2021","C02 per capita (t CO2\/yr)":0.092365424,"total C02 emissions (Mt CO2\/yr)":1.235757002,"Cumulative CO\u2082 emissions (1970\u20132021 in Mt CO2)":31.006721777,"C02 per GDP (t CO2\/yr)":0.040999758},{"EDGAR Country Code":"SAU","Country":"Saudi Arabia","year":"2021","C02 per capita (t CO2\/yr)":16.62927841,"total C02 emissions (Mt CO2\/yr)":586.3982445,"Cumulative CO\u2082 emissions (1970\u20132021 in Mt CO2)":14952.66429542,"C02 per GDP (t CO2\/yr)":0.36787479},{"EDGAR Country Code":"SCG","Country":"Serbia and Montenegro","year":"2021","C02 per capita (t CO2\/yr)":4.229780323,"total C02 emissions (Mt CO2\/yr)":39.34964635,"Cumulative CO\u2082 emissions (1970\u20132021 in Mt CO2)":2743.36226398,"C02 per GDP (t CO2\/yr)":0.232947399},{"EDGAR Country Code":"SDN","Country":"Sudan and South Sudan","year":"2021","C02 per capita (t CO2\/yr)":0.360221012,"total C02 emissions (Mt CO2\/yr)":21.36578888,"Cumulative CO\u2082 emissions (1970\u20132021 in Mt CO2)":474.620716418,"C02 per GDP (t CO2\/yr)":0.123934854},{"EDGAR Country Code":"SEN","Country":"Senegal","year":"2021","C02 per capita (t CO2\/yr)":0.678300623,"total C02 emissions (Mt CO2\/yr)":11.9808239,"Cumulative CO\u2082 emissions (1970\u20132021 in Mt CO2)":236.382469958,"C02 per GDP (t CO2\/yr)":0.203095972},{"EDGAR Country Code":"SGP","Country":"Singapore","year":"2021","C02 per capita (t CO2\/yr)":9.709857402,"total C02 emissions (Mt CO2\/yr)":58.18146555,"Cumulative CO\u2082 emissions (1970\u20132021 in Mt CO2)":1757.858760656,"C02 per GDP (t CO2\/yr)":0.100615806},{"EDGAR Country Code":"SHN","Country":"Saint Helena, Ascension and Tristan da Cunha","year":"2021","C02 per capita (t CO2\/yr)":4.025404776,"total C02 emissions (Mt CO2\/yr)":0.016101619,"Cumulative CO\u2082 emissions (1970\u20132021 in Mt CO2)":0.383869652,"C02 per GDP (t CO2\/yr)":null},{"EDGAR Country Code":"SLB","Country":"Solomon Islands","year":"2021","C02 per capita (t CO2\/yr)":0.498356149,"total C02 emissions (Mt CO2\/yr)":0.328915059,"Cumulative CO\u2082 emissions (1970\u20132021 in Mt CO2)":11.041924844,"C02 per GDP (t CO2\/yr)":0.193244563},{"EDGAR Country Code":"SLE","Country":"Sierra Leone","year":"2021","C02 per capita (t CO2\/yr)":0.122868355,"total C02 emissions (Mt CO2\/yr)":1.008872059,"Cumulative CO\u2082 emissions (1970\u20132021 in Mt CO2)":37.678714559,"C02 per GDP (t CO2\/yr)":0.074958537},{"EDGAR Country Code":"SLV","Country":"El Salvador","year":"2021","C02 per capita (t CO2\/yr)":1.255410176,"total C02 emissions (Mt CO2\/yr)":8.176486479,"Cumulative CO\u2082 emissions (1970\u20132021 in Mt CO2)":247.763399349,"C02 per GDP (t CO2\/yr)":0.142523791},{"EDGAR Country Code":"SOM","Country":"Somalia","year":"2021","C02 per capita (t CO2\/yr)":0.046032262,"total C02 emissions (Mt CO2\/yr)":0.763629187,"Cumulative CO\u2082 emissions (1970\u20132021 in Mt CO2)":40.356478224,"C02 per GDP (t CO2\/yr)":0.039372067},{"EDGAR Country Code":"SPM","Country":"Saint Pierre and Miquelon","year":"2021","C02 per capita (t CO2\/yr)":13.25309296,"total C02 emissions (Mt CO2\/yr)":0.092771651,"Cumulative CO\u2082 emissions (1970\u20132021 in Mt CO2)":9.297198908,"C02 per GDP (t CO2\/yr)":null},{"EDGAR Country Code":"STP","Country":"S\u00e3o Tom\u00e9 and Pr\u00edncipe","year":"2021","C02 per capita (t CO2\/yr)":0.68816914,"total C02 emissions (Mt CO2\/yr)":0.153461718,"Cumulative CO\u2082 emissions (1970\u20132021 in Mt CO2)":3.615730707,"C02 per GDP (t CO2\/yr)":0.169770381},{"EDGAR Country Code":"SUR","Country":"Suriname","year":"2021","C02 per capita (t CO2\/yr)":4.643168712,"total C02 emissions (Mt CO2\/yr)":2.706967359,"Cumulative CO\u2082 emissions (1970\u20132021 in Mt CO2)":92.993952486,"C02 per GDP (t CO2\/yr)":0.301345479},{"EDGAR Country Code":"SVK","Country":"Slovakia","year":"2021","C02 per capita (t CO2\/yr)":6.87613464,"total C02 emissions (Mt CO2\/yr)":37.48180992,"Cumulative CO\u2082 emissions (1970\u20132021 in Mt CO2)":2437.32090042,"C02 per GDP (t CO2\/yr)":0.218453378},{"EDGAR Country Code":"SVN","Country":"Slovenia","year":"2021","C02 per capita (t CO2\/yr)":6.806276291,"total C02 emissions (Mt CO2\/yr)":14.17066724,"Cumulative CO\u2082 emissions (1970\u20132021 in Mt CO2)":756.030019726,"C02 per GDP (t CO2\/yr)":0.168264391},{"EDGAR Country Code":"SWE","Country":"Sweden","year":"2021","C02 per capita (t CO2\/yr)":3.820354094,"total C02 emissions (Mt CO2\/yr)":38.92176751,"Cumulative CO\u2082 emissions (1970\u20132021 in Mt CO2)":3281.94087743,"C02 per GDP (t CO2\/yr)":0.070438711},{"EDGAR Country Code":"SWZ","Country":"Eswatini","year":"2021","C02 per capita (t CO2\/yr)":1.031175719,"total C02 emissions (Mt CO2\/yr)":1.508610076,"Cumulative CO\u2082 emissions (1970\u20132021 in Mt CO2)":76.132340418,"C02 per GDP (t CO2\/yr)":0.144020415},{"EDGAR Country Code":"SYC","Country":"Seychelles","year":"2021","C02 per capita (t CO2\/yr)":10.78754126,"total C02 emissions (Mt CO2\/yr)":1.046391503,"Cumulative CO\u2082 emissions (1970\u20132021 in Mt CO2)":29.112954473,"C02 per GDP (t CO2\/yr)":0.38837344},{"EDGAR Country Code":"SYR","Country":"Syria","year":"2021","C02 per capita (t CO2\/yr)":1.320289285,"total C02 emissions (Mt CO2\/yr)":25.86050622,"Cumulative CO\u2082 emissions (1970\u20132021 in Mt CO2)":1690.047621051,"C02 per GDP (t CO2\/yr)":0.548271035},{"EDGAR Country Code":"TCA","Country":"Turks and Caicos Islands","year":"2021","C02 per capita (t CO2\/yr)":6.715933791,"total C02 emissions (Mt CO2\/yr)":0.24848955,"Cumulative CO\u2082 emissions (1970\u20132021 in Mt CO2)":7.255293146,"C02 per GDP (t CO2\/yr)":0.297531336},{"EDGAR Country Code":"TCD","Country":"Chad","year":"2021","C02 per capita (t CO2\/yr)":0.132065982,"total C02 emissions (Mt CO2\/yr)":2.21421826,"Cumulative CO\u2082 emissions (1970\u20132021 in Mt CO2)":29.917066397,"C02 per GDP (t CO2\/yr)":0.090414543},{"EDGAR Country Code":"TGO","Country":"Togo","year":"2021","C02 per capita (t CO2\/yr)":0.262802486,"total C02 emissions (Mt CO2\/yr)":2.256159345,"Cumulative CO\u2082 emissions (1970\u20132021 in Mt CO2)":57.61791717,"C02 per GDP (t CO2\/yr)":0.122827169},{"EDGAR Country Code":"THA","Country":"Thailand","year":"2021","C02 per capita (t CO2\/yr)":3.878769382,"total C02 emissions (Mt CO2\/yr)":269.5667145,"Cumulative CO\u2082 emissions (1970\u20132021 in Mt CO2)":7564.4252425,"C02 per GDP (t CO2\/yr)":0.220391601},{"EDGAR Country Code":"TJK","Country":"Tajikistan","year":"2021","C02 per capita (t CO2\/yr)":1.048671339,"total C02 emissions (Mt CO2\/yr)":10.12597045,"Cumulative CO\u2082 emissions (1970\u20132021 in Mt CO2)":371.836046088,"C02 per GDP (t CO2\/yr)":0.266069462},{"EDGAR Country Code":"TKM","Country":"Turkmenistan","year":"2021","C02 per capita (t CO2\/yr)":13.62131729,"total C02 emissions (Mt CO2\/yr)":83.32159784,"Cumulative CO\u2082 emissions (1970\u20132021 in Mt CO2)":2304.87827084,"C02 per GDP (t CO2\/yr)":0.853596756},{"EDGAR Country Code":"TLS","Country":"Timor-Leste","year":"2021","C02 per capita (t CO2\/yr)":0.401533589,"total C02 emissions (Mt CO2\/yr)":0.566563894,"Cumulative CO\u2082 emissions (1970\u20132021 in Mt CO2)":10.117573001,"C02 per GDP (t CO2\/yr)":0.104843814},{"EDGAR Country Code":"TON","Country":"Tonga","year":"2021","C02 per capita (t CO2\/yr)":1.508934367,"total C02 emissions (Mt CO2\/yr)":0.169000649,"Cumulative CO\u2082 emissions (1970\u20132021 in Mt CO2)":4.69948499,"C02 per GDP (t CO2\/yr)":0.253723457},{"EDGAR Country Code":"TTO","Country":"Trinidad and Tobago","year":"2021","C02 per capita (t CO2\/yr)":21.01054242,"total C02 emissions (Mt CO2\/yr)":28.99454855,"Cumulative CO\u2082 emissions (1970\u20132021 in Mt CO2)":1035.916159903,"C02 per GDP (t CO2\/yr)":0.844780167},{"EDGAR Country Code":"TUN","Country":"Tunisia","year":"2021","C02 per capita (t CO2\/yr)":2.644645232,"total C02 emissions (Mt CO2\/yr)":31.78599104,"Cumulative CO\u2082 emissions (1970\u20132021 in Mt CO2)":929.871643505,"C02 per GDP (t CO2\/yr)":0.252326501},{"EDGAR Country Code":"TUR","Country":"Turkey","year":"2021","C02 per capita (t CO2\/yr)":5.321306552,"total C02 emissions (Mt CO2\/yr)":449.724902,"Cumulative CO\u2082 emissions (1970\u20132021 in Mt CO2)":10645.81088335,"C02 per GDP (t CO2\/yr)":0.169211871},{"EDGAR Country Code":"TWN","Country":"Taiwan","year":"2021","C02 per capita (t CO2\/yr)":12.07041608,"total C02 emissions (Mt CO2\/yr)":288.157043,"Cumulative CO\u2082 emissions (1970\u20132021 in Mt CO2)":8933.82985524,"C02 per GDP (t CO2\/yr)":0.241102317},{"EDGAR Country Code":"TZA","Country":"Tanzania","year":"2021","C02 per capita (t CO2\/yr)":0.207311758,"total C02 emissions (Mt CO2\/yr)":13.40768066,"Cumulative CO\u2082 emissions (1970\u20132021 in Mt CO2)":245.509990821,"C02 per GDP (t CO2\/yr)":0.084152438},{"EDGAR Country Code":"UGA","Country":"Uganda","year":"2021","C02 per capita (t CO2\/yr)":0.139958731,"total C02 emissions (Mt CO2\/yr)":6.815710279,"Cumulative CO\u2082 emissions (1970\u20132021 in Mt CO2)":111.379315256,"C02 per GDP (t CO2\/yr)":0.066268175},{"EDGAR Country Code":"UKR","Country":"Ukraine","year":"2021","C02 per capita (t CO2\/yr)":4.277009293,"total C02 emissions (Mt CO2\/yr)":185.4554,"Cumulative CO\u2082 emissions (1970\u20132021 in Mt CO2)":25899.092167,"C02 per GDP (t CO2\/yr)":0.346270942},{"EDGAR Country Code":"URY","Country":"Uruguay","year":"2021","C02 per capita (t CO2\/yr)":1.93671328,"total C02 emissions (Mt CO2\/yr)":6.790116761,"Cumulative CO\u2082 emissions (1970\u20132021 in Mt CO2)":293.011806345,"C02 per GDP (t CO2\/yr)":0.086917843},{"EDGAR Country Code":"USA","Country":"United States","year":"2021","C02 per capita (t CO2\/yr)":14.2370322,"total C02 emissions (Mt CO2\/yr)":4752.07932,"Cumulative CO\u2082 emissions (1970\u20132021 in Mt CO2)":270585.488348,"C02 per GDP (t CO2\/yr)":0.227021566},{"EDGAR Country Code":"UZB","Country":"Uzbekistan","year":"2021","C02 per capita (t CO2\/yr)":3.73424537,"total C02 emissions (Mt CO2\/yr)":125.6536225,"Cumulative CO\u2082 emissions (1970\u20132021 in Mt CO2)":5430.61829761,"C02 per GDP (t CO2\/yr)":0.465276175},{"EDGAR Country Code":"VCT","Country":"Saint Vincent and the Grenadines","year":"2021","C02 per capita (t CO2\/yr)":2.097664369,"total C02 emissions (Mt CO2\/yr)":0.232840745,"Cumulative CO\u2082 emissions (1970\u20132021 in Mt CO2)":10.3304238,"C02 per GDP (t CO2\/yr)":0.163957062},{"EDGAR Country Code":"VEN","Country":"Venezuela","year":"2021","C02 per capita (t CO2\/yr)":3.119057738,"total C02 emissions (Mt CO2\/yr)":104.6724586,"Cumulative CO\u2082 emissions (1970\u20132021 in Mt CO2)":6118.41743946,"C02 per GDP (t CO2\/yr)":0.186778356},{"EDGAR Country Code":"VGB","Country":"British Virgin Islands","year":"2021","C02 per capita (t CO2\/yr)":5.525057736,"total C02 emissions (Mt CO2\/yr)":0.182326905,"Cumulative CO\u2082 emissions (1970\u20132021 in Mt CO2)":7.819611986,"C02 per GDP (t CO2\/yr)":0.167547828},{"EDGAR Country Code":"VNM","Country":"Vietnam","year":"2021","C02 per capita (t CO2\/yr)":3.23731254,"total C02 emissions (Mt CO2\/yr)":321.4133382,"Cumulative CO\u2082 emissions (1970\u20132021 in Mt CO2)":4399.22417931,"C02 per GDP (t CO2\/yr)":0.311336835},{"EDGAR Country Code":"VUT","Country":"Vanuatu","year":"2021","C02 per capita (t CO2\/yr)":0.743388115,"total C02 emissions (Mt CO2\/yr)":0.223016434,"Cumulative CO\u2082 emissions (1970\u20132021 in Mt CO2)":5.847998177,"C02 per GDP (t CO2\/yr)":0.25091176},{"EDGAR Country Code":"WSM","Country":"Samoa","year":"2021","C02 per capita (t CO2\/yr)":1.783314711,"total C02 emissions (Mt CO2\/yr)":0.360229572,"Cumulative CO\u2082 emissions (1970\u20132021 in Mt CO2)":9.103404316,"C02 per GDP (t CO2\/yr)":0.307974958},{"EDGAR Country Code":"YEM","Country":"Yemen","year":"2021","C02 per capita (t CO2\/yr)":0.389739748,"total C02 emissions (Mt CO2\/yr)":12.04724534,"Cumulative CO\u2082 emissions (1970\u20132021 in Mt CO2)":607.459237134,"C02 per GDP (t CO2\/yr)":0.097881421},{"EDGAR Country Code":"ZAF","Country":"South Africa","year":"2021","C02 per capita (t CO2\/yr)":7.336233057,"total C02 emissions (Mt CO2\/yr)":435.5228117,"Cumulative CO\u2082 emissions (1970\u20132021 in Mt CO2)":17855.9575392,"C02 per GDP (t CO2\/yr)":0.552615292},{"EDGAR Country Code":"ZMB","Country":"Zambia","year":"2021","C02 per capita (t CO2\/yr)":0.364490015,"total C02 emissions (Mt CO2\/yr)":7.010965431,"Cumulative CO\u2082 emissions (1970\u20132021 in Mt CO2)":191.757831059,"C02 per GDP (t CO2\/yr)":0.112333278},{"EDGAR Country Code":"ZWE","Country":"Zimbabwe","year":"2021","C02 per capita (t CO2\/yr)":0.680688121,"total C02 emissions (Mt CO2\/yr)":12.29322746,"Cumulative CO\u2082 emissions (1970\u20132021 in Mt CO2)":632.703663784,"C02 per GDP (t CO2\/yr)":0.233016281}]